simplenlopt/_Core.py
simplenlopt/_Curve_Fit.py
simplenlopt/_Global_Optimization.py
simplenlopt/__init__.py
simplenlopt/_helpers.py
simplenlopt-1.1.dist-info/LICENSE
simplenlopt-1.1.dist-info/METADATA
simplenlopt-1.1.dist-info/WHEEL
simplenlopt-1.1.dist-info/top_level.txt
simplenlopt-1.1.dist-info/RECORD
