Metadata-Version: 2.1
Name: simplenlopt
Version: 1.1
Summary: A scipy.optimize like API for nlopt
Home-page: https://github.com/dschmitz89/simplenlopt/
Author: Daniel Schmitz
Author-email: danielschmitzsiegen@gmail.com
License: Apache 2
Download-URL: https://github.com/dschmitz89/simplenlopt/archive/refs/tags/1.0.tar.gz
Platform: UNKNOWN
Requires-Dist: numpy
Requires-Dist: scipy (>=1.2)
Requires-Dist: nlopt (>=2.7)
